docs/__init__.py
docs/conf.py
edx_management_commands/__init__.py
edx_management_commands/settings.py
edx_management_commands/management_commands/__init__.py
edx_management_commands/management_commands/tests.py
edx_management_commands/management_commands/urls.py
edx_management_commands/management_commands/views.py
edx_management_commands/management_commands/management/__init__.py
edx_management_commands/management_commands/management/commands/__init__.py
edx_management_commands/management_commands/management/commands/manage_group.py
edx_management_commands/management_commands/management/commands/manage_user.py
edx_management_commands-0.1.1.dist-info/DESCRIPTION.rst
edx_management_commands-0.1.1.dist-info/METADATA
edx_management_commands-0.1.1.dist-info/RECORD
edx_management_commands-0.1.1.dist-info/WHEEL
edx_management_commands-0.1.1.dist-info/metadata.json
edx_management_commands-0.1.1.dist-info/top_level.txt
