Metadata-Version: 2.0
Name: edx-management-commands
Version: 0.1.1
Summary: Reusable automation and configuration utilities for edX Django applications
Home-page: https://github.com/edx/edx-django-extensions
Author: edX
Author-email: UNKNOWN
License: AGPL
Platform: UNKNOWN
Classifier: Development Status :: 3 - Alpha
Classifier: Environment :: Web Environment
Classifier: Intended Audience :: Developers
Classifier: License :: OSI Approved :: GNU Affero General Public License v3
Classifier: Operating System :: OS Independent
Classifier: Programming Language :: Python
Classifier: Framework :: Django
Requires-Dist: django (>=1.8.7,<1.9)
